AUTHORS
CONTRIBUTING.rst
ChangeLog
HACKING.rst
LICENSE
README.rst
babel.cfg
requirements.txt
setup.cfg
setup.py
test-requirements.txt
tox.ini
networking_l2gw_tempest_plugin.egg-info/PKG-INFO
networking_l2gw_tempest_plugin.egg-info/SOURCES.txt
networking_l2gw_tempest_plugin.egg-info/dependency_links.txt
networking_l2gw_tempest_plugin.egg-info/entry_points.txt
networking_l2gw_tempest_plugin.egg-info/not-zip-safe
networking_l2gw_tempest_plugin.egg-info/pbr.json
networking_l2gw_tempest_plugin.egg-info/requires.txt
networking_l2gw_tempest_plugin.egg-info/top_level.txt
networking_l2gw_tempest_plugin/tests/__init__.py
networking_l2gw_tempest_plugin/tests/api/__init__.py
networking_l2gw_tempest_plugin/tests/api/base_l2gw.py
networking_l2gw_tempest_plugin/tests/api/test_l2gw_extensions.py
networking_l2gw_tempest_plugin/tests/api/test_l2gw_negative.py
networking_l2gw_tempest_plugin/tests/fullstack/__init__.py
networking_l2gw_tempest_plugin/tests/fullstack/test_l2gw.py
networking_l2gw_tempest_plugin/tests/scenario/__init__.py
networking_l2gw_tempest_plugin/tests/scenario/ovsdb_connections.py
networking_l2gw_tempest_plugin/tests/scenario/test_l2gateways.py
networking_l2gw_tempest_plugin/tests/tempest/__init__.py
networking_l2gw_tempest_plugin/tests/tempest/config.py
networking_l2gw_tempest_plugin/tests/tempest/plugin.py